Mini_CNN/cnn_param.v
//Parameterized Mini CNN Compute Unit(For bonus points consideration)
// This module Supports: MAC, ReLU, MaxPooling, Overflow Detection 
//Problem Statement 1: Mini CNN compute unit
//Our proposed solution is a parameterized Verilog module that implements a mini CNN compute unit capable of performing MAC, ReLU, and MaxPooling operations with overflow detection. 
//The module is designed to be flexible, allowing the window size to be adjusted through parameters.

module mini_cnn_param #(
    parameter integer WINDOW = 3,
    parameter integer ACC_WIDTH = 32
)(
    input  wire                     clk,
    input  wire                     reset,
    input  wire [1:0]               mode_select,     // 00: MAC, 01: ReLU, 10: MaxPool
    input  wire signed [7:0]        data_in,         // signed 8-bit input data
    input  wire                     load_enable,     // high to start loading memory
    input  wire                     start_operation, // one-cycle pulse to start processing

    output reg  signed [ACC_WIDTH-1:0] result_out,   // 32-bit signed output
    output reg                        busy,          // high when active
    output reg  [15:0]                current_index,  // debug index
    output reg                        overflow_flag   // high on signed overflow
);

    
    // Derived parameters
    localparam integer NN = WINDOW * WINDOW;
    localparam integer MEM_SIZE = 2 * NN; // pixels + kernels

    // Internal memory    
    reg signed [7:0] data_memory [0:MEM_SIZE-1];

    // FSM States    
    reg [2:0] op_state;
    localparam STATE_IDLE      = 3'd0;
    localparam STATE_LOAD_DATA = 3'd1;
    localparam STATE_RUNNING   = 3'd2;

    // Core registers    
    reg [15:0] index;
    reg signed [ACC_WIDTH-1:0] accumulator_reg;
    reg signed [ACC_WIDTH-1:0] max_pool_reg;
    reg signed [ACC_WIDTH-1:0] product_ext;
    reg signed [ACC_WIDTH-1:0] sum_temp;
    reg start_r;
    reg overflow_this_cycle;

    // Constants    
    localparam MODE_MAC      = 2'b00;
    localparam MODE_RELU     = 2'b01;
    localparam MODE_MAX_POOL = 2'b10;

    wire signed [ACC_WIDTH-1:0] ACC_MAX = {1'b0, {(ACC_WIDTH-1){1'b1}}};
    wire signed [ACC_WIDTH-1:0] ACC_MIN = {1'b1, {(ACC_WIDTH-1){1'b0}}};

    // Main Sequential Logic    
    always @(posedge clk or posedge reset) begin
        if (reset) begin
            result_out <= 0;
            busy <= 0;
            op_state <= STATE_IDLE;
            index <= 0;
            accumulator_reg <= 0;
            max_pool_reg <= -ACC_MIN; // most negative value
            current_index <= 0;
            start_r <= 0;
            overflow_flag <= 0;
        end else begin
            start_r <= start_operation;

            case (op_state)
                // STATE_IDLE
                STATE_IDLE: begin
                    if (load_enable) begin
                        busy <= 1;
                        index <= 0;
                        op_state <= STATE_LOAD_DATA;
                    end else if (start_operation && !start_r) begin
                        busy <= 1;
                        index <= 0;
                        accumulator_reg <= 0;
                        max_pool_reg <= -ACC_MIN;
                        overflow_flag <= 0;
                        op_state <= STATE_RUNNING;
                    end
                end

                // STATE_LOAD_DATA
                STATE_LOAD_DATA: begin
                    data_memory[index] <= data_in;
                    current_index <= index;
                    index <= index + 1;

                    if (index == MEM_SIZE - 1) begin
                        busy <= 0;
                        op_state <= STATE_IDLE;
                    end
                end

                // STATE_RUNNING
                STATE_RUNNING: begin
                    current_index <= index;

                    // Signed multiply and sum
                    product_ext = $signed(data_memory[index]) * $signed(data_memory[index + NN]);
                    sum_temp = accumulator_reg + product_ext;

                    // Detect overflow
                    overflow_this_cycle = ((accumulator_reg[ACC_WIDTH-1] == product_ext[ACC_WIDTH-1]) &&
                                            (sum_temp[ACC_WIDTH-1] != accumulator_reg[ACC_WIDTH-1]));
                    if (overflow_this_cycle)
                        overflow_flag <= 1;

                    accumulator_reg <= sum_temp;

                    // Max pooling
                    if (product_ext > max_pool_reg)
                        max_pool_reg <= product_ext;

                    // Final cycle
                    if (index == NN - 1) begin
                        case (mode_select)
                            MODE_MAC: begin
                                if (overflow_flag)
                                    result_out <= (accumulator_reg[ACC_WIDTH-1]) ? ACC_MIN : ACC_MAX;
                                else
                                    result_out <= sum_temp;
                            end

                            MODE_RELU: begin
                                if (overflow_flag)
                                    result_out <= (accumulator_reg[ACC_WIDTH-1]) ? 0 : ACC_MAX;
                                else if (sum_temp < 0)
                                    result_out <= 0;
                                else
                                    result_out <= sum_temp;
                            end

                            MODE_MAX_POOL: begin
                                if (product_ext > max_pool_reg)
                                    result_out <= product_ext;
                                else
                                    result_out <= max_pool_reg;
                            end
                        endcase

                        busy <= 0;
                        op_state <= STATE_IDLE;
                    end else begin
                        index <= index + 1;
                    end
                end
            endcase
        end
    end
endmodule

Mini_CNN/cnn_param_tb.v
`timescale 1ns/1ps
module testbench_mini_cnn_param();

    parameter integer WINDOW = 5;               // Adjustable window size --> as of now we have set to 5
    localparam integer NN = WINDOW * WINDOW;
    localparam integer MEM_SIZE = 2 * NN;

    reg clk, reset;
    reg [1:0] mode_select;
    reg [7:0] data_in;
    reg load_enable, start_operation;

    wire signed [31:0] result_out;
    wire busy;
    wire [15:0] current_index;
    wire overflow_flag;

    // DUT
    mini_cnn_param #(.WINDOW(WINDOW)) UUT (
        .clk(clk), .reset(reset), .mode_select(mode_select),
        .data_in(data_in), .load_enable(load_enable), .start_operation(start_operation),
        .result_out(result_out), .busy(busy),
        .current_index(current_index), .overflow_flag(overflow_flag)
    );

    reg [7:0] test_data [0:(2*WINDOW*WINDOW)-1];
    integer i;
    integer sum_expected;

    // Clock
    initial begin
        clk = 0;
        forever #5 clk = ~clk;
    end

    // Load data into memory
    task load_all;
        begin
            load_enable = 1;
            #10;
            for (i = 0; i < MEM_SIZE; i = i + 1) begin
                data_in = test_data[i];
                #10;
            end
            load_enable = 0;
            wait(busy == 0);
            #10;
        end
    endtask

    // Run operation
    task run_op;
        begin
            start_operation = 1;
            #10;
            start_operation = 0;
            wait(busy == 0);
            #10;
        end
    endtask

    initial begin
        reset = 1; load_enable = 0; start_operation = 0; data_in = 0;
        #15 reset = 0;
        $display("[%0t] Reset complete", $time);

        $display("\n--- Test 1: MaxPool ---");
        for (i = 0; i < NN; i = i + 1)
            test_data[i] = i + 1; // 1..NN
        for (i = 0; i < NN; i = i + 1)
            test_data[NN + i] = 8'd1;

        load_all();
        mode_select = 2'b10;
        run_op();
        $display("MaxPool result=%0d overflow=%b", result_out, overflow_flag);
        $display("Expected max value = %0d\n", NN);

        $display("\n--- Test 2: ReLU ---");
        for (i = 0; i < NN; i = i + 1) begin
            if (i < NN/2)
                test_data[i] = -8'd5; // negative half
            else
                test_data[i] = 8'd5;  // positive half
            test_data[NN + i] = 8'd1;
        end

        load_all();
        mode_select = 2'b01;
        run_op();

        sum_expected = 0;
        for (i = 0; i < NN; i = i + 1)
            sum_expected = sum_expected + $signed(test_data[i]) * $signed(test_data[NN + i]);
        if (sum_expected < 0)
            sum_expected = 0;
        $display("ReLU result=%0d expected=%0d overflow=%b\n",
                 result_out, sum_expected, overflow_flag);

        $display("\n--- Test 3: MAC ---");
        for (i = 0; i < NN; i = i + 1) begin
            test_data[i] = i + 1;
            test_data[NN + i] = 8'd1;
        end

        load_all();
        mode_select = 2'b00;
        run_op();

        sum_expected = 0;
        for (i = 1; i <= NN; i = i + 1)
            sum_expected = sum_expected + i;
        $display("MAC result=%0d expected=%0d overflow=%b\n",
                 result_out, sum_expected, overflow_flag);

        $display("\n--- Test 4: Overflow Demo ---");
        for (i = 0; i < NN; i = i + 1) begin
            test_data[i] = 8'd120;
            test_data[NN + i] = 8'd120;
        end

        load_all();
        mode_select = 2'b00;
        run_op();
        $display("Overflow Test result=%0d overflow=%b\n",
                 result_out, overflow_flag);

        #50 $finish;
    end

    initial begin
        $dumpfile("mini_cnn_param_wave.vcd");
        $dumpvars(0, testbench_mini_cnn_param);
    end
endmodule

Mini_CNN/mini_cnn_param_wave.vcd
$date
	Sat Nov 08 20:36:11 2025
$end
$version
	Icarus Verilog
$end
$timescale
	1ps
$end
$scope module testbench_mini_cnn_param $end
$var wire 32 ! result_out [31:0] $end
$var wire 1 " overflow_flag $end
$var wire 16 # current_index [15:0] $end
$var wire 1 $ busy $end
$var parameter 32 % MEM_SIZE $end
$var parameter 32 & NN $end
$var parameter 32 ' WINDOW $end
$var reg 1 ( clk $end
$var reg 8 ) data_in [7:0] $end
$var reg 1 * load_enable $end
$var reg 2 + mode_select [1:0] $end
$var reg 1 , reset $end
$var reg 1 - start_operation $end
$var integer 32 . i [31:0] $end
$var integer 32 / sum_expected [31:0] $end
$scope module UUT $end
$var wire 32 0 ACC_MAX [31:0] $end
$var wire 32 1 ACC_MIN [31:0] $end
$var wire 1 ( clk $end
$var wire 8 2 data_in [7:0] $end
$var wire 1 * load_enable $end
$var wire 2 3 mode_select [1:0] $end
$var wire 1 , reset $end
$var wire 1 - start_operation $end
$var parameter 32 4 ACC_WIDTH $end
$var parameter 32 5 MEM_SIZE $end
$var parameter 2 6 MODE_MAC $end
$var parameter 2 7 MODE_MAX_POOL $end
$var parameter 2 8 MODE_RELU $end
$var parameter 32 9 NN $end
$var parameter 3 : STATE_IDLE $end
$var parameter 3 ; STATE_LOAD_DATA $end
$var parameter 3 < STATE_RUNNING $end
$var parameter 32 = WINDOW $end
$var reg 32 > accumulator_reg [31:0] $end
$var reg 1 $ busy $end
$var reg 16 ? current_index [15:0] $end
$var reg 16 @ index [15:0] $end
$var reg 32 A max_pool_reg [31:0] $end
$var reg 3 B op_state [2:0] $end
$var reg 1 " overflow_flag $end
$var reg 1 C overflow_this_cycle $end
$var reg 32 D product_ext [31:0] $end
$var reg 32 E result_out [31:0] $end
$var reg 1 F start_r $end
$var reg 32 G sum_temp [31:0] $end
$upscope $end
$scope task load_all $end
$upscope $end
$scope task run_op $end
$upscope $end
$upscope $end
$enddefinitions $end
$comment Show the parameter values. $end
$dumpall
b101 =
b10 <
b1 ;
b0 :
b11001 9
b1 8
b10 7
b0 6
b110010 5
b100000 4
b101 '
b11001 &
b110010 %
$end
#0
$dumpvars
bx G
0F
b0 E
bx D
xC
b0 B
b10000000000000000000000000000000 A
b0 @
b0 ?
b0 >
bx 3
b0 2
b10000000000000000000000000000000 1
b1111111111111111111111111111111 0
bx /
bx .
0-
1,
bx +
0*
b0 )
0(
0$
b0 #
0"
b0 !
$end
#5000
1(
#10000
0(
#15000
b1 B
1$
1(
1*
b11001 .
0,
#20000
0(
#25000
b1 @
1(
b1 )
b1 2
b0 .
#30000
0(
#35000
b10 @
b1 #
b1 ?
1(
b10 )
b10 2
b1 .
#40000
0(
#45000
b11 @
b10 #
b10 ?
1(
b11 )
b11 2
b10 .
#50000
0(
#55000
b100 @
b11 #
b11 ?
1(
b100 )
b100 2
b11 .
#60000
0(
#65000
b101 @
b100 #
b100 ?
1(
b101 )
b101 2
b100 .
#70000
0(
#75000
b110 @
b101 #
b101 ?
1(
b110 )
b110 2
b101 .
#80000
0(
#85000
b111 @
b110 #
b110 ?
1(
b111 )
b111 2
b110 .
#90000
0(
#95000
b1000 @
b111 #
b111 ?
1(
b1000 )
b1000 2
b111 .
#100000
0(
#105000
b1001 @
b1000 #
b1000 ?
1(
b1001 )
b1001 2
b1000 .
#110000
0(
#115000
b1010 @
b1001 #
b1001 ?
1(
b1010 )
b1010 2
b1001 .
#120000
0(
#125000
b1011 @
b1010 #
b1010 ?
1(
b1011 )
b1011 2
b1010 .
#130000
0(
#135000
b1100 @
b1011 #
b1011 ?
1(
b1100 )
b1100 2
b1011 .
#140000
0(
#145000
b1101 @
b1100 #
b1100 ?
1(
b1101 )
b1101 2
b1100 .
#150000
0(
#155000
b1110 @
b1101 #
b1101 ?
1(
b1110 )
b1110 2
b1101 .
#160000
0(
#165000
b1111 @
b1110 #
b1110 ?
1(
b1111 )
b1111 2
b1110 .
#170000
0(
#175000
b10000 @
b1111 #
b1111 ?
1(
b10000 )
b10000 2
b1111 .
#180000
0(
#185000
b10001 @
b10000 #
b10000 ?
1(
b10001 )
b10001 2
b10000 .
#190000
0(
#195000
b10010 @
b10001 #
b10001 ?
1(
b10010 )
b10010 2
b10001 .
#200000
0(
#205000
b10011 @
b10010 #
b10010 ?
1(
b10011 )
b10011 2
b10010 .
#210000
0(
#215000
b10100 @
b10011 #
b10011 ?
1(
b10100 )
b10100 2
b10011 .
#220000
0(
#225000
b10101 @
b10100 #
b10100 ?
1(
b10101 )
b10101 2
b10100 .
#230000
0(
#235000
b10110 @
b10101 #
b10101 ?
1(
b10110 )
b10110 2
b10101 .
#240000
0(
#245000
b10111 @
b10110 #
b10110 ?
1(
b10111 )
b10111 2
b10110 .
#250000
0(
#255000
b11000 @
b10111 #
b10111 ?
1(
b11000 )
b11000 2
b10111 .
#260000
0(
#265000
b11001 @
b11000 #
b11000 ?
1(
b11001 )
b11001 2
b11000 .
#270000
0(
#275000
b11010 @
b11001 #
b11001 ?
1(
b1 )
b1 2
b11001 .
#280000
0(
#285000
b11011 @
b11010 #
b11010 ?
1(
b11010 .
#290000
0(
#295000
b11100 @
b11011 #
b11011 ?
1(
b11011 .
#300000
0(
#305000
b11101 @
b11100 #
b11100 ?
1(
b11100 .
#310000
0(
#315000
b11110 @
b11101 #
b11101 ?
1(
b11101 .
#320000
0(
#325000
b11111 @
b11110 #
b11110 ?
1(
b11110 .
#330000
0(
#335000
b100000 @
b11111 #
b11111 ?
1(
b11111 .
#340000
0(
#345000
b100001 @
b100000 #
b100000 ?
1(
b100000 .
#350000
0(
#355000
b100010 @
b100001 #
b100001 ?
1(
b100001 .
#360000
0(
#365000
b100011 @
b100010 #
b100010 ?
1(
b100010 .
#370000
0(
#375000
b100100 @
b100011 #
b100011 ?
1(
b100011 .
#380000
0(
#385000
b100101 @
b100100 #
b100100 ?
1(
b100100 .
#390000
0(
#395000
b100110 @
b100101 #
b100101 ?
1(
b100101 .
#400000
0(
#405000
b100111 @
b100110 #
b100110 ?
1(
b100110 .
#410000
0(
#415000
b101000 @
b100111 #
b100111 ?
1(
b100111 .
#420000
0(
#425000
b101001 @
b101000 #
b101000 ?
1(
b101000 .
#430000
0(
#435000
b101010 @
b101001 #
b101001 ?
1(
b101001 .
#440000
0(
#445000
b101011 @
b101010 #
b101010 ?
1(
b101010 .
#450000
0(
#455000
b101100 @
b101011 #
b101011 ?
1(
b101011 .
#460000
0(
#465000
b101101 @
b101100 #
b101100 ?
1(
b101100 .
#470000
0(
#475000
b101110 @
b101101 #
b101101 ?
1(
b101101 .
#480000
0(
#485000
b101111 @
b101110 #
b101110 ?
1(
b101110 .
#490000
0(
#495000
b110000 @
b101111 #
b101111 ?
1(
b101111 .
#500000
0(
#505000
b110001 @
b110000 #
b110000 ?
1(
b110000 .
#510000
0(
#515000
b0 B
0$
b110010 @
b110001 #
b110001 ?
1(
b110001 .
#520000
0(
#525000
1(
0*
b110010 .
#530000
0(
#535000
b10 B
b0 @
1$
1F
1(
1-
b10 +
b10 3
#540000
0(
#545000
b1 @
b1 A
b1 >
b0 #
b0 ?
0F
0C
b1 G
b1 D
1(
0-
#550000
0(
#555000
b10 @
b10 A
b11 >
b1 #
b1 ?
b11 G
b10 D
1(
#560000
0(
#565000
b11 @
b11 A
b110 >
b10 #
b10 ?
b110 G
b11 D
1(
#570000
0(
#575000
b100 @
b100 A
b1010 >
b11 #
b11 ?
b1010 G
b100 D
1(
#580000
0(
#585000
b101 @
b101 A
b1111 >
b100 #
b100 ?
b1111 G
b101 D
1(
#590000
0(
#595000
b110 @
b110 A
b10101 >
b101 #
b101 ?
b10101 G
b110 D
1(
#600000
0(
#605000
b111 @
b111 A
b11100 >
b110 #
b110 ?
b11100 G
b111 D
1(
#610000
0(
#615000
b1000 @
b1000 A
b100100 >
b111 #
b111 ?
b100100 G
b1000 D
1(
#620000
0(
#625000
b1001 @
b1001 A
b101101 >
b1000 #
b1000 ?
b101101 G
b1001 D
1(
#630000
0(
#635000
b1010 @
b1010 A
b110111 >
b1001 #
b1001 ?
b110111 G
b1010 D
1(
#640000
0(
#645000
b1011 @
b1011 A
b1000010 >
b1010 #
b1010 ?
b1000010 G
b1011 D
1(
#650000
0(
#655000
b1100 @
b1100 A
b1001110 >
b1011 #
b1011 ?
b1001110 G
b1100 D
1(
#660000
0(
#665000
b1101 @
b1101 A
b1011011 >
b1100 #
b1100 ?
b1011011 G
b1101 D
1(
#670000
0(
#675000
b1110 @
b1110 A
b1101001 >
b1101 #
b1101 ?
b1101001 G
b1110 D
1(
#680000
0(
#685000
b1111 @
b1111 A
b1111000 >
b1110 #
b1110 ?
b1111000 G
b1111 D
1(
#690000
0(
#695000
b10000 @
b10000 A
b10001000 >
b1111 #
b1111 ?
b10001000 G
b10000 D
1(
#700000
0(
#705000
b10001 @
b10001 A
b10011001 >
b10000 #
b10000 ?
b10011001 G
b10001 D
1(
#710000
0(
#715000
b10010 @
b10010 A
b10101011 >
b10001 #
b10001 ?
b10101011 G
b10010 D
1(
#720000
0(
#725000
b10011 @
b10011 A
b10111110 >
b10010 #
b10010 ?
b10111110 G
b10011 D
1(
#730000
0(
#735000
b10100 @
b10100 A
b11010010 >
b10011 #
b10011 ?
b11010010 G
b10100 D
1(
#740000
0(
#745000
b10101 @
b10101 A
b11100111 >
b10100 #
b10100 ?
b11100111 G
b10101 D
1(
#750000
0(
#755000
b10110 @
b10110 A
b11111101 >
b10101 #
b10101 ?
b11111101 G
b10110 D
1(
#760000
0(
#765000
b10111 @
b10111 A
b100010100 >
b10110 #
b10110 ?
b100010100 G
b10111 D
1(
#770000
0(
#775000
b11000 @
b11000 A
b100101100 >
b10111 #
b10111 ?
b100101100 G
b11000 D
1(
#780000
0(
#785000
b0 B
0$
b11001 !
b11001 E
b11001 A
b101000101 >
b11000 #
b11000 ?
b101000101 G
b11001 D
1(
#790000
0(
#795000
b1 B
b0 @
1$
1(
1*
b11001 .
#800000
0(
#805000
b1 @
b0 #
b0 ?
1(
b11111011 )
b11111011 2
b0 .
#810000
0(
#815000
b10 @
b1 #
b1 ?
1(
b1 .
#820000
0(
#825000
b11 @
b10 #
b10 ?
1(
b10 .
#830000
0(
#835000
b100 @
b11 #
b11 ?
1(
b11 .
#840000
0(
#845000
b101 @
b100 #
b100 ?
1(
b100 .
#850000
0(
#855000
b110 @
b101 #
b101 ?
1(
b101 .
#860000
0(
#865000
b111 @
b110 #
b110 ?
1(
b110 .
#870000
0(
#875000
b1000 @
b111 #
b111 ?
1(
b111 .
#880000
0(
#885000
b1001 @
b1000 #
b1000 ?
1(
b1000 .
#890000
0(
#895000
b1010 @
b1001 #
b1001 ?
1(
b1001 .
#900000
0(
#905000
b1011 @
b1010 #
b1010 ?
1(
b1010 .
#910000
0(
#915000
b1100 @
b1011 #
b1011 ?
1(
b1011 .
#920000
0(
#925000
b1101 @
b1100 #
b1100 ?
1(
b101 )
b101 2
b1100 .
#930000
0(
#935000
b1110 @
b1101 #
b1101 ?
1(
b1101 .
#940000
0(
#945000
b1111 @
b1110 #
b1110 ?
1(
b1110 .
#950000
0(
#955000
b10000 @
b1111 #
b1111 ?
1(
b1111 .
#960000
0(
#965000
b10001 @
b10000 #
b10000 ?
1(
b10000 .
#970000
0(
#975000
b10010 @
b10001 #
b10001 ?
1(
b10001 .
#980000
0(
#985000
b10011 @
b10010 #
b10010 ?
1(
b10010 .
#990000
0(
#995000
b10100 @
b10011 #
b10011 ?
1(
b10011 .
#1000000
0(
#1005000
b10101 @
b10100 #
b10100 ?
1(
b10100 .
#1010000
0(
#1015000
b10110 @
b10101 #
b10101 ?
1(
b10101 .
#1020000
0(
#1025000
b10111 @
b10110 #
b10110 ?
1(
b10110 .
#1030000
0(
#1035000
b11000 @
b10111 #
b10111 ?
1(
b10111 .
#1040000
0(
#1045000
b11001 @
b11000 #
b11000 ?
1(
b11000 .
#1050000
0(
#1055000
b11010 @
b11001 #
b11001 ?
1(
b1 )
b1 2
b11001 .
#1060000
0(
#1065000
b11011 @
b11010 #
b11010 ?
1(
b11010 .
#1070000
0(
#1075000
b11100 @
b11011 #
b11011 ?
1(
b11011 .
#1080000
0(
#1085000
b11101 @
b11100 #
b11100 ?
1(
b11100 .
#1090000
0(
#1095000
b11110 @
b11101 #
b11101 ?
1(
b11101 .
#1100000
0(
#1105000
b11111 @
b11110 #
b11110 ?
1(
b11110 .
#1110000
0(
#1115000
b100000 @
b11111 #
b11111 ?
1(
b11111 .
#1120000
0(
#1125000
b100001 @
b100000 #
b100000 ?
1(
b100000 .
#1130000
0(
#1135000
b100010 @
b100001 #
b100001 ?
1(
b100001 .
#1140000
0(
#1145000
b100011 @
b100010 #
b100010 ?
1(
b100010 .
#1150000
0(
#1155000
b100100 @
b100011 #
b100011 ?
1(
b100011 .
#1160000
0(
#1165000
b100101 @
b100100 #
b100100 ?
1(
b100100 .
#1170000
0(
#1175000
b100110 @
b100101 #
b100101 ?
1(
b100101 .
#1180000
0(
#1185000
b100111 @
b100110 #
b100110 ?
1(
b100110 .
#1190000
0(
#1195000
b101000 @
b100111 #
b100111 ?
1(
b100111 .
#1200000
0(
#1205000
b101001 @
b101000 #
b101000 ?
1(
b101000 .
#1210000
0(
#1215000
b101010 @
b101001 #
b101001 ?
1(
b101001 .
#1220000
0(
#1225000
b101011 @
b101010 #
b101010 ?
1(
b101010 .
#1230000
0(
#1235000
b101100 @
b101011 #
b101011 ?
1(
b101011 .
#1240000
0(
#1245000
b101101 @
b101100 #
b101100 ?
1(
b101100 .
#1250000
0(
#1255000
b101110 @
b101101 #
b101101 ?
1(
b101101 .
#1260000
0(
#1265000
b101111 @
b101110 #
b101110 ?
1(
b101110 .
#1270000
0(
#1275000
b110000 @
b101111 #
b101111 ?
1(
b101111 .
#1280000
0(
#1285000
b110001 @
b110000 #
b110000 ?
1(
b110000 .
#1290000
0(
#1295000
b0 B
0$
b110010 @
b110001 #
b110001 ?
1(
b110001 .
#1300000
0(
#1305000
1(
0*
b110010 .
#1310000
0(
#1315000
b10 B
b10000000000000000000000000000000 A
b0 >
b0 @
1$
1F
1(
1-
b1 +
b1 3
#1320000
0(
#1325000
b1 @
b11111111111111111111111111111011 A
b11111111111111111111111111111011 >
b0 #
b0 ?
0F
b11111111111111111111111111111011 G
b11111111111111111111111111111011 D
1(
0-
#1330000
0(
#1335000
b10 @
b11111111111111111111111111110110 >
b1 #
b1 ?
b11111111111111111111111111110110 G
1(
#1340000
0(
#1345000
b11 @
b11111111111111111111111111110001 >
b10 #
b10 ?
b11111111111111111111111111110001 G
1(
#1350000
0(
#1355000
b100 @
b11111111111111111111111111101100 >
b11 #
b11 ?
b11111111111111111111111111101100 G
1(
#1360000
0(
#1365000
b101 @
b11111111111111111111111111100111 >
b100 #
b100 ?
b11111111111111111111111111100111 G
1(
#1370000
0(
#1375000
b110 @
b11111111111111111111111111100010 >
b101 #
b101 ?
b11111111111111111111111111100010 G
1(
#1380000
0(
#1385000
b111 @
b11111111111111111111111111011101 >
b110 #
b110 ?
b11111111111111111111111111011101 G
1(
#1390000
0(
#1395000
b1000 @
b11111111111111111111111111011000 >
b111 #
b111 ?
b11111111111111111111111111011000 G
1(
#1400000
0(
#1405000
b1001 @
b11111111111111111111111111010011 >
b1000 #
b1000 ?
b11111111111111111111111111010011 G
1(
#1410000
0(
#1415000
b1010 @
b11111111111111111111111111001110 >
b1001 #
b1001 ?
b11111111111111111111111111001110 G
1(
#1420000
0(
#1425000
b1011 @
b11111111111111111111111111001001 >
b1010 #
b1010 ?
b11111111111111111111111111001001 G
1(
#1430000
0(
#1435000
b1100 @
b11111111111111111111111111000100 >
b1011 #
b1011 ?
b11111111111111111111111111000100 G
1(
#1440000
0(
#1445000
b1101 @
b101 A
b11111111111111111111111111001001 >
b1100 #
b1100 ?
b11111111111111111111111111001001 G
b101 D
1(
#1450000
0(
#1455000
b1110 @
b11111111111111111111111111001110 >
b1101 #
b1101 ?
b11111111111111111111111111001110 G
1(
#1460000
0(
#1465000
b1111 @
b11111111111111111111111111010011 >
b1110 #
b1110 ?
b11111111111111111111111111010011 G
1(
#1470000
0(
#1475000
b10000 @
b11111111111111111111111111011000 >
b1111 #
b1111 ?
b11111111111111111111111111011000 G
1(
#1480000
0(
#1485000
b10001 @
b11111111111111111111111111011101 >
b10000 #
b10000 ?
b11111111111111111111111111011101 G
1(
#1490000
0(
#1495000
b10010 @
b11111111111111111111111111100010 >
b10001 #
b10001 ?
b11111111111111111111111111100010 G
1(
#1500000
0(
#1505000
b10011 @
b11111111111111111111111111100111 >
b10010 #
b10010 ?
b11111111111111111111111111100111 G
1(
#1510000
0(
#1515000
b10100 @
b11111111111111111111111111101100 >
b10011 #
b10011 ?
b11111111111111111111111111101100 G
1(
#1520000
0(
#1525000
b10101 @
b11111111111111111111111111110001 >
b10100 #
b10100 ?
b11111111111111111111111111110001 G
1(
#1530000
0(
#1535000
b10110 @
b11111111111111111111111111110110 >
b10101 #
b10101 ?
b11111111111111111111111111110110 G
1(
#1540000
0(
#1545000
b10111 @
b11111111111111111111111111111011 >
b10110 #
b10110 ?
b11111111111111111111111111111011 G
1(
#1550000
0(
#1555000
b11000 @
b0 >
b10111 #
b10111 ?
b0 G
1(
#1560000
0(
#1565000
b0 B
0$
b101 !
b101 E
b101 >
b11000 #
b11000 ?
b101 G
1(
#1570000
0(
#1575000
b1 B
b0 @
1$
1(
1*
b11001 .
b101 /
#1580000
0(
#1585000
b1 @
b0 #
b0 ?
1(
b0 .
#1590000
0(
#1595000
b10 @
b1 #
b1 ?
1(
b10 )
b10 2
b1 .
#1600000
0(
#1605000
b11 @
b10 #
b10 ?
1(
b11 )
b11 2
b10 .
#1610000
0(
#1615000
b100 @
b11 #
b11 ?
1(
b100 )
b100 2
b11 .
#1620000
0(
#1625000
b101 @
b100 #
b100 ?
1(
b101 )
b101 2
b100 .
#1630000
0(
#1635000
b110 @
b101 #
b101 ?
1(
b110 )
b110 2
b101 .
#1640000
0(
#1645000
b111 @
b110 #
b110 ?
1(
b111 )
b111 2
b110 .
#1650000
0(
#1655000
b1000 @
b111 #
b111 ?
1(
b1000 )
b1000 2
b111 .
#1660000
0(
#1665000
b1001 @
b1000 #
b1000 ?
1(
b1001 )
b1001 2
b1000 .
#1670000
0(
#1675000
b1010 @
b1001 #
b1001 ?
1(
b1010 )
b1010 2
b1001 .
#1680000
0(
#1685000
b1011 @
b1010 #
b1010 ?
1(
b1011 )
b1011 2
b1010 .
#1690000
0(
#1695000
b1100 @
b1011 #
b1011 ?
1(
b1100 )
b1100 2
b1011 .
#1700000
0(
#1705000
b1101 @
b1100 #
b1100 ?
1(
b1101 )
b1101 2
b1100 .
#1710000
0(
#1715000
b1110 @
b1101 #
b1101 ?
1(
b1110 )
b1110 2
b1101 .
#1720000
0(
#1725000
b1111 @
b1110 #
b1110 ?
1(
b1111 )
b1111 2
b1110 .
#1730000
0(
#1735000
b10000 @
b1111 #
b1111 ?
1(
b10000 )
b10000 2
b1111 .
#1740000
0(
#1745000
b10001 @
b10000 #
b10000 ?
1(
b10001 )
b10001 2
b10000 .
#1750000
0(
#1755000
b10010 @
b10001 #
b10001 ?
1(
b10010 )
b10010 2
b10001 .
#1760000
0(
#1765000
b10011 @
b10010 #
b10010 ?
1(
b10011 )
b10011 2
b10010 .
#1770000
0(
#1775000
b10100 @
b10011 #
b10011 ?
1(
b10100 )
b10100 2
b10011 .
#1780000
0(
#1785000
b10101 @
b10100 #
b10100 ?
1(
b10101 )
b10101 2
b10100 .
#1790000
0(
#1795000
b10110 @
b10101 #
b10101 ?
1(
b10110 )
b10110 2
b10101 .
#1800000
0(
#1805000
b10111 @
b10110 #
b10110 ?
1(
b10111 )
b10111 2
b10110 .
#1810000
0(
#1815000
b11000 @
b10111 #
b10111 ?
1(
b11000 )
b11000 2
b10111 .
#1820000
0(
#1825000
b11001 @
b11000 #
b11000 ?
1(
b11001 )
b11001 2
b11000 .
#1830000
0(
#1835000
b11010 @
b11001 #
b11001 ?
1(
b1 )
b1 2
b11001 .
#1840000
0(
#1845000
b11011 @
b11010 #
b11010 ?
1(
b11010 .
#1850000
0(
#1855000
b11100 @
b11011 #
b11011 ?
1(
b11011 .
#1860000
0(
#1865000
b11101 @
b11100 #
b11100 ?
1(
b11100 .
#1870000
0(
#1875000
b11110 @
b11101 #
b11101 ?
1(
b11101 .
#1880000
0(
#1885000
b11111 @
b11110 #
b11110 ?
1(
b11110 .
#1890000
0(
#1895000
b100000 @
b11111 #
b11111 ?
1(
b11111 .
#1900000
0(
#1905000
b100001 @
b100000 #
b100000 ?
1(
b100000 .
#1910000
0(
#1915000
b100010 @
b100001 #
b100001 ?
1(
b100001 .
#1920000
0(
#1925000
b100011 @
b100010 #
b100010 ?
1(
b100010 .
#1930000
0(
#1935000
b100100 @
b100011 #
b100011 ?
1(
b100011 .
#1940000
0(
#1945000
b100101 @
b100100 #
b100100 ?
1(
b100100 .
#1950000
0(
#1955000
b100110 @
b100101 #
b100101 ?
1(
b100101 .
#1960000
0(
#1965000
b100111 @
b100110 #
b100110 ?
1(
b100110 .
#1970000
0(
#1975000
b101000 @
b100111 #
b100111 ?
1(
b100111 .
#1980000
0(
#1985000
b101001 @
b101000 #
b101000 ?
1(
b101000 .
#1990000
0(
#1995000
b101010 @
b101001 #
b101001 ?
1(
b101001 .
#2000000
0(
#2005000
b101011 @
b101010 #
b101010 ?
1(
b101010 .
#2010000
0(
#2015000
b101100 @
b101011 #
b101011 ?
1(
b101011 .
#2020000
0(
#2025000
b101101 @
b101100 #
b101100 ?
1(
b101100 .
#2030000
0(
#2035000
b101110 @
b101101 #
b101101 ?
1(
b101101 .
#2040000
0(
#2045000
b101111 @
b101110 #
b101110 ?
1(
b101110 .
#2050000
0(
#2055000
b110000 @
b101111 #
b101111 ?
1(
b101111 .
#2060000
0(
#2065000
b110001 @
b110000 #
b110000 ?
1(
b110000 .
#2070000
0(
#2075000
b0 B
0$
b110010 @
b110001 #
b110001 ?
1(
b110001 .
#2080000
0(
#2085000
1(
0*
b110010 .
#2090000
0(
