4_bit_ALU_IIITD/customizedOperations.v
module custom (
    input  wire [3:0] A,
    input  wire [3:0] B,
    input  wire [1:0] custom_sel, // 2'b00: logical left shift, 2'b01: logical right shift, 2'b10: rotate left, 2'b11: popcount(A|B)
    output reg  [7:0] result
);
    wire [1:0] shamt = B[1:0];
    reg  [3:0] shifted;
    integer i;
    function [2:0] popcount4;
        input [3:0] v;
        integer j;
        begin
            popcount4 = 0;
            for (j = 0; j < 4; j = j + 1)
                popcount4 = popcount4 + v[j];
        end
    endfunction

    always @(*) begin
        case (custom_sel)
            2'b00: begin // logical left shift
                shifted = (A << shamt);
                result = {4'b0000, shifted};
            end
            2'b01: begin // logical right shift
                shifted = (A >> shamt);
                result = {4'b0000, shifted};
            end
            2'b10: begin // rotate left
                case (shamt)
                    2'd0: shifted = A;
                    2'd1: shifted = {A[2:0], A[3]};
                    2'd2: shifted = {A[1:0], A[3:2]};
                    2'd3: shifted = {A[0], A[3:1]};
                    default: shifted = A;
                endcase
                result = {4'b0000, shifted};
            end
            2'b11: begin // popcount of (A | B)
                result = {5'b00000, popcount4(A | B)}; // small number, place in LSBs
            end
            default: result = 8'b0;
        endcase
    end
endmodule

4_bit_ALU_IIITD/logical_operations.v
module logic_ops #(parameter WIDTH = 4) (
    input  [WIDTH-1:0] A, B,
    input  [1:0] sel,   // 00: AND, 01: OR, 10: XOR
    output reg [2*WIDTH-1:0] result,
    output reg carry_out
);
    always @(*) begin
        case (sel)
            2'b00: result = { {WIDTH{1'b0}}, (A & B) };  // AND
            2'b01: result = { {WIDTH{1'b0}}, (A | B) };  // OR
            2'b10: result = { {WIDTH{1'b0}}, (A ^ B) };  // XOR
            default: result = {2*WIDTH{1'b0}};
        endcase
        carry_out = 1'b0;  // Logic ops don’t produce carry
    end
endmodule

4_bit_ALU_IIITD/division.v
module div #(parameter WIDTH = 4) (
    input [WIDTH-1:0] A, B,
    output [2*WIDTH-1:0] result,
    output carry_out  // 1 if divide-by-zero
);
    assign result[2*WIDTH-1:WIDTH] = (B == 0) ? 0 : (A / B);  // Quotient
    assign result[WIDTH-1:0] = (B == 0) ? 0 : (A % B);       // Remainder
    assign carry_out = (B == 0) ? 1 : 0;  // Error flag
endmodule

4_bit_ALU_IIITD/multiplication.v
module mul #(parameter WIDTH = 4) (
    input [WIDTH-1:0] A, B,
    output [2*WIDTH-1:0] result,
    output carry_out  // Always 0, as 8-bit output fits
);
    assign result = A * B;  // 4x4 multiplication
    assign carry_out = 0;
endmodule

4_bit_ALU_IIITD/subtraction.v
module sub #(parameter WIDTH = 4) (
    input [WIDTH-1:0] A, B,
    output [2*WIDTH-1:0] result,
    output carry_out  // Borrow flag
);
    assign {carry_out, result[WIDTH-1:0]} = A - B;  // Sub with borrow
    assign result[2*WIDTH-1:WIDTH] = 0;
endmodule

4_bit_ALU_IIITD/addition.v
module add #(parameter WIDTH = 4) (
    input [WIDTH-1:0] A, B,
    output [2*WIDTH-1:0] result,  // 8-bit for 4-bit inputs
    output carry_out
);
    assign {carry_out, result[WIDTH-1:0]} = A + B;  // Add with carry
    assign result[2*WIDTH-1:WIDTH] = 0;  // Zero-extend upper bits
endmodule

4_bit_ALU_IIITD/alu_top.v
module alu_top #(parameter WIDTH = 4) (
    input  [WIDTH-1:0] A, B,
    input  [2:0] opcode,
    output reg [2*WIDTH-1:0] result,
    output reg carry_out
);

    // Wires for each module's outputs
    wire [2*WIDTH-1:0] add_res, sub_res, mul_res, div_res, logic_res, custom_res;
    wire add_co, sub_co, mul_co, div_co, logic_co;

    // Instantiate operation modules
    add  #(.WIDTH(WIDTH)) u_add (.A(A), .B(B), .result(add_res), .carry_out(add_co));
    sub  #(.WIDTH(WIDTH)) u_sub (.A(A), .B(B), .result(sub_res), .carry_out(sub_co));
    mul  #(.WIDTH(WIDTH)) u_mul (.A(A), .B(B), .result(mul_res), .carry_out(mul_co));
    div  #(.WIDTH(WIDTH)) u_div (.A(A), .B(B), .result(div_res), .carry_out(div_co));
    logic_ops #(.WIDTH(WIDTH)) u_logic (.A(A), .B(B), .sel(opcode[1:0]), .result(logic_res), .carry_out(logic_co));
    custom u_custom (.A(A), .B(B), .custom_sel(B[1:0]), .result(custom_res));

    // Multiplexer to select based on opcode
    always @(*) begin
        case (opcode)
            3'b000: begin result = add_res;   carry_out = add_co;   end
            3'b001: begin result = sub_res;   carry_out = sub_co;   end
            3'b010: begin result = mul_res;   carry_out = mul_co;   end
            3'b011: begin result = div_res;   carry_out = div_co;   end
            3'b100, 3'b101, 3'b110: begin result = logic_res; carry_out = logic_co; end
            3'b111: begin result = custom_res; carry_out = 0; end
            default: begin result = 0; carry_out = 0; end
        endcase
    end
endmodule

4_bit_ALU_IIITD/alu_tb.v
`timescale 1ns/1ps
module alu_tb;
    parameter WIDTH = 4;
    reg [WIDTH-1:0] A, B;
    reg [2:0] opcode;
    wire [2*WIDTH-1:0] result;
    wire carry_out;

    // Instantiate DUT
    alu_top #(.WIDTH(WIDTH)) dut (
        .A(A), .B(B), .opcode(opcode), .result(result), .carry_out(carry_out)
    );

    initial begin
        $dumpfile("alu_tb.vcd");
        $dumpvars(0, alu_tb);
        $monitor("Time=%0t | A=%b | B=%b | opcode=%03b | result=%08b | carry_out=%b",
          $time, A, B, opcode, result, carry_out);


        // Test cases for all opcodes
        A = 4'b1010; B = 4'b0101; opcode = 3'b000; #10; // Add
        opcode = 3'b001; #10; // Sub
        opcode = 3'b010; #10; // Mul
        opcode = 3'b011; #10; // Div
        opcode = 3'b100; #10; // AND
        opcode = 3'b101; #10; // OR
        opcode = 3'b110; #10; // XOR

        // Custom operations (opcode = 111)
        B = 4'b0001; opcode = 3'b111; #10;
        B = 4'b0010; opcode = 3'b111; #10;
        B = 4'b0011; opcode = 3'b111; #10;

        // Edge cases
        A = 4'b1111; B = 4'b0001; opcode = 3'b000; #10;
        A = 4'b0000; B = 4'b0000; opcode = 3'b011; #10;
        A = 4'b1100; B = 4'b0000; opcode = 3'b111; #10;

        // Random tests for coverage
        repeat(20) begin
            A = $random % (1<<WIDTH);
            B = $random % (1<<WIDTH);
            opcode = $random % 8;
            #10;
        end

        $finish;
    end
endmodule

4_bit_ALU_IIITD/alu_tb.vcd
$date
	Mon Nov 03 16:08:52 2025
$end
$version
	Icarus Verilog
$end
$timescale
	1ps
$end
$scope module alu_tb $end
$var wire 8 ! result [7:0] $end
$var wire 1 " carry_out $end
$var parameter 32 # WIDTH $end
$var reg 4 $ A [3:0] $end
$var reg 4 % B [3:0] $end
$var reg 3 & opcode [2:0] $end
$scope module dut $end
$var wire 4 ' A [3:0] $end
$var wire 4 ( B [3:0] $end
$var wire 1 ) mul_co $end
$var wire 3 * opcode [2:0] $end
$var wire 8 + sub_res [7:0] $end
$var wire 1 , sub_co $end
$var wire 8 - mul_res [7:0] $end
$var wire 8 . logic_res [7:0] $end
$var wire 1 / logic_co $end
$var wire 8 0 div_res [7:0] $end
$var wire 1 1 div_co $end
$var wire 8 2 custom_res [7:0] $end
$var wire 8 3 add_res [7:0] $end
$var wire 1 4 add_co $end
$var parameter 32 5 WIDTH $end
$var reg 1 " carry_out $end
$var reg 8 6 result [7:0] $end
$scope module u_add $end
$var wire 4 7 A [3:0] $end
$var wire 4 8 B [3:0] $end
$var wire 8 9 result [7:0] $end
$var wire 1 4 carry_out $end
$var parameter 32 : WIDTH $end
$upscope $end
$scope module u_custom $end
$var wire 4 ; A [3:0] $end
$var wire 4 < B [3:0] $end
$var wire 2 = custom_sel [1:0] $end
$var wire 2 > shamt [1:0] $end
$var reg 8 ? result [7:0] $end
$var reg 4 @ shifted [3:0] $end
$scope function popcount4 $end
$var reg 4 A v [3:0] $end
$var integer 32 B j [31:0] $end
$upscope $end
$upscope $end
$scope module u_div $end
$var wire 4 C A [3:0] $end
$var wire 4 D B [3:0] $end
$var wire 8 E result [7:0] $end
$var wire 1 1 carry_out $end
$var parameter 32 F WIDTH $end
$upscope $end
$scope module u_logic $end
$var wire 4 G A [3:0] $end
$var wire 4 H B [3:0] $end
$var wire 2 I sel [1:0] $end
$var parameter 32 J WIDTH $end
$var reg 1 / carry_out $end
$var reg 8 K result [7:0] $end
$upscope $end
$scope module u_mul $end
$var wire 4 L A [3:0] $end
$var wire 4 M B [3:0] $end
$var wire 1 ) carry_out $end
$var wire 8 N result [7:0] $end
$var parameter 32 O WIDTH $end
$upscope $end
$scope module u_sub $end
$var wire 4 P A [3:0] $end
$var wire 4 Q B [3:0] $end
$var wire 8 R result [7:0] $end
$var wire 1 , carry_out $end
$var parameter 32 S WIDTH $end
$upscope $end
$upscope $end
$upscope $end
$enddefinitions $end
$comment Show the parameter values. $end
$dumpall
b100 S
b100 O
b100 J
b100 F
b100 :
b100 5
b100 #
$end
#0
$dumpvars
b101 R
b101 Q
b1010 P
b110010 N
b101 M
b1010 L
b0 K
b0 I
b101 H
b1010 G
b100000 E
b101 D
b1010 C
bx B
bx A
b101 @
b101 ?
b1 >
b1 =
b101 <
b1010 ;
b1111 9
b101 8
b1010 7
b1111 6
04
b1111 3
b101 2
01
b100000 0
0/
b0 .
b110010 -
0,
b101 +
b0 *
0)
b101 (
b1010 '
b0 &
b101 %
b1010 $
0"
b1111 !
$end
#10000
b1111 .
b1111 K
b101 !
b101 6
b1 I
b1 &
b1 *
#20000
b110010 !
b110010 6
b10 I
b10 &
b10 *
#30000
b0 .
b0 K
b100000 !
b100000 6
b11 I
b11 &
b11 *
#40000
b0 !
b0 6
b0 I
b100 &
b100 *
#50000
b1111 !
b1111 6
b1111 .
b1111 K
b1 I
b101 &
b101 *
#60000
b10 I
b110 &
b110 *
#70000
b10100000 0
b10100000 E
b11 I
b1011 3
b1011 9
b0 .
b0 K
b101 !
b101 6
b1001 +
b1001 R
b111 &
b111 *
b1010 -
b1010 N
b1 %
b1 (
b1 8
b1 <
b1 D
b1 H
b1 M
b1 Q
#80000
b1010 !
b1010 6
b1010000 0
b1010000 E
b10 =
b1100 3
b1100 9
b1010 2
b1010 ?
b1010 @
b10 >
b1000 +
b1000 R
b10100 -
b10100 N
b10 %
b10 (
b10 8
b10 <
b10 D
b10 H
b10 M
b10 Q
#90000
b100 B
b1011 A
b11 !
b11 6
b110001 0
b110001 E
b11 =
b1101 3
b1101 9
b11 2
b11 ?
b101 @
b11 >
b111 +
b111 R
b11110 -
b11110 N
b11 %
b11 (
b11 8
b11 <
b11 D
b11 H
b11 M
b11 Q
#100000
b1 .
b1 K
b111 @
1"
b11110000 0
b11110000 E
b0 I
b1 =
b1 >
b0 3
b0 9
14
b111 2
b111 ?
b100 B
b1111 A
b0 !
b0 6
b1110 +
b1110 R
b0 &
b0 *
b1 %
b1 (
b1 8
b1 <
b1 D
b1 H
b1 M
b1 Q
b1111 -
b1111 N
b1111 $
b1111 '
b1111 7
b1111 ;
b1111 C
b1111 G
b1111 L
b1111 P
#110000
11
b0 0
b0 E
b11 I
b0 =
b0 >
04
b0 2
b0 ?
b0 @
b0 .
b0 K
1"
b0 !
b0 6
b0 +
b0 R
b11 &
b11 *
b0 %
b0 (
b0 8
b0 <
b0 D
b0 H
b0 M
b0 Q
b0 -
b0 N
b0 $
b0 '
b0 7
b0 ;
b0 C
b0 G
b0 L
b0 P
#120000
0"
b1100 !
b1100 6
b1100 3
b1100 9
b1100 2
b1100 ?
b1100 @
b1100 +
b1100 R
b111 &
b111 *
b1100 $
b1100 '
b1100 7
b1100 ;
b1100 C
b1100 G
b1100 L
b1100 P
#130000
b101 .
b101 K
b1000000 0
b1000000 E
01
b1 I
b1 =
b1 >
b11 !
b11 6
b101 3
b101 9
b10 2
b10 ?
b10 @
b11 +
b11 R
b1 &
b1 *
b100 -
b100 N
b1 %
b1 (
b1 8
b1 <
b1 D
b1 H
b1 M
b1 Q
b100 $
b100 '
b100 7
b100 ;
b100 C
b100 G
b100 L
b100 P
#140000
b11 0
b11 E
14
1,
b0 3
b0 9
b1 2
b1 ?
b1 @
b1111 .
b1111 K
b1111 !
b1111 6
b110 +
b110 R
b101 &
b101 *
b1101 %
b1101 (
b1101 8
b1101 <
b1101 D
b1101 H
b1101 M
b1101 Q
b100111 -
b100111 N
b11 $
b11 '
b11 7
b11 ;
b11 C
b11 G
b11 L
b11 P
#150000
b100001 0
b100001 E
b10 =
04
b10 >
0,
b111 3
b111 9
b101 2
b101 ?
b101 @
b111 .
b111 K
0"
b11 !
b11 6
b11 +
b11 R
b1 &
b1 *
b10 %
b10 (
b10 8
b10 <
b10 D
b10 H
b10 M
b10 Q
b1010 -
b1010 N
b101 $
b101 '
b101 7
b101 ;
b101 C
b101 G
b101 L
b101 P
#160000
14
b11 3
b11 9
b111 2
b111 ?
b111 @
b1111 .
b1111 K
b1111 !
b1111 6
b111 +
b111 R
b101 &
b101 *
b110 %
b110 (
b110 8
b110 <
b110 D
b110 H
b110 M
b110 Q
b1001110 -
b1001110 N
b1101 $
b1101 '
b1101 7
b1101 ;
b1101 C
b1101 G
b1101 L
b1101 P
#170000
b10001 0
b10001 E
b0 =
b1001 3
b1001 9
b1101 2
b1101 ?
b1101 @
b0 >
b1101 .
b1101 K
b1 !
b1 6
b1 +
b1 R
b1 &
b1 *
b10011100 -
b10011100 N
b1100 %
b1100 (
b1100 8
b1100 <
b1100 D
b1100 H
b1100 M
b1100 Q
#180000
b10 I
b1 =
04
b1 >
b1011 3
b1011 9
b11 2
b11 ?
b11 @
b11 .
b11 K
b11110 !
b11110 6
b10 &
b10 *
b101 %
b101 (
b101 8
b101 <
b101 D
b101 H
b101 M
b101 Q
b11110 -
b11110 N
b110 $
b110 '
b110 7
b110 ;
b110 C
b110 G
b110 L
b110 P
#190000
b100 B
b111 A
b101 0
b101 E
b11 =
b11 >
1,
b1100 3
b1100 9
b11 2
b11 ?
b10 @
b10 .
b10 K
b100011 !
b100011 6
b1110 +
b1110 R
b111 %
b111 (
b111 8
b111 <
b111 D
b111 H
b111 M
b111 Q
b100011 -
b100011 N
b101 $
b101 '
b101 7
b101 ;
b101 C
b101 G
b101 L
b101 P
#200000
b1111 @
b1110001 0
b1110001 E
b10 =
b10 >
b1 3
b1 9
14
b1111 2
b1111 ?
b100 B
b1111 A
b1101 .
b1101 K
b1101 !
b1101 6
b1101 +
b1101 R
0,
b110 &
b110 *
b10 %
b10 (
b10 8
b10 <
b10 D
b10 H
b10 M
b10 Q
b11110 -
b11110 N
b1111 $
b1111 '
b1111 7
b1111 ;
b1111 C
b1111 G
b1111 L
b1111 P
#210000
b0 !
b0 6
b0 .
b0 K
b10011 0
b10011 E
b0 I
b1 =
b1 >
b1101 3
b1101 9
04
b100 2
b100 ?
b100 @
b11 +
b11 R
b100 &
b100 *
b101 %
b101 (
b101 8
b101 <
b101 D
b101 H
b101 M
b101 Q
b101000 -
b101000 N
b1000 $
b1000 '
b1000 7
b1000 ;
b1000 C
b1000 G
b1000 L
b1000 P
#220000
b10000 0
b10000 E
b1101 !
b1101 6
b1 I
b1010 3
b1010 9
14
b110 2
b110 ?
b110 @
b1101 .
b1101 K
b0 +
b0 R
b101 &
b101 *
b1101 %
b1101 (
b1101 8
b1101 <
b1101 D
b1101 H
b1101 M
b1101 Q
b10101001 -
b10101001 N
b1101 $
b1101 '
b1101 7
b1101 ;
b1101 C
b1101 G
b1101 L
b1101 P
#230000
b11 0
b11 E
b0 I
b10 =
04
b10 >
b1101 3
b1101 9
b1100 2
b1100 ?
b1100 @
b10 .
b10 K
0"
b1101 !
b1101 6
b1001 +
b1001 R
1,
b0 &
b0 *
b1010 %
b1010 (
b1010 8
b1010 <
b1010 D
b1010 H
b1010 M
b1010 Q
b11110 -
b11110 N
b11 $
b11 '
b11 7
b11 ;
b11 C
b11 G
b11 L
b11 P
#240000
b0 0
b0 E
b1 I
b1010 3
b1010 9
b0 2
b0 ?
b0 @
b1010 .
b1010 K
b1010 !
b1010 6
b110 +
b110 R
b101 &
b101 *
b0 -
b0 N
b0 $
b0 '
b0 7
b0 ;
b0 C
b0 G
b0 L
b0 P
#250000
b100 B
b111 A
b100000 0
b100000 E
b111 !
b111 6
b11 =
b11 >
0,
b1001 3
b1001 9
b11 2
b11 ?
b1001 @
b111 .
b111 K
b11 +
b11 R
b11 %
b11 (
b11 8
b11 <
b11 D
b11 H
b11 M
b11 Q
b10010 -
b10010 N
b110 $
b110 '
b110 7
b110 ;
b110 C
b110 G
b110 L
b110 P
#260000
b11 0
b11 E
b1011 !
b1011 6
1,
b1110 3
b1110 9
b100 B
b1011 A
b1011 .
b1011 K
b1000 +
b1000 R
b1011 %
b1011 (
b1011 8
b1011 <
b1011 D
b1011 H
b1011 M
b1011 Q
b100001 -
b100001 N
b11 $
b11 '
b11 7
b11 ;
b11 C
b11 G
b11 L
b11 P
#270000
b1000 2
b1000 ?
b1000 @
b10 0
b10 E
b1110 !
b1110 6
b10 =
14
b10 >
b0 3
b0 9
b100 B
b1110 A
b1110 .
b1110 K
b100 +
b100 R
b1110 %
b1110 (
b1110 8
b1110 <
b1110 D
b1110 H
b1110 M
b1110 Q
b11100 -
b11100 N
b10 $
b10 '
b10 7
b10 ;
b10 C
b10 G
b10 L
b10 P
#280000
b100 B
b1111 A
b1010000 0
b1010000 E
b10 I
b11 =
b11 >
b10 3
b10 9
b100 2
b100 ?
b1111 @
b1100 .
b1100 K
b101101 !
b101101 6
b1100 +
b1100 R
0,
b10 &
b10 *
b11 %
b11 (
b11 8
b11 <
b11 D
b11 H
b11 M
b11 Q
b101101 -
b101101 N
b1111 $
b1111 '
b1111 7
b1111 ;
b1111 C
b1111 G
b1111 L
b1111 P
#290000
b1010 @
b1010 0
b1010 E
b0 =
b0 >
1,
b110 3
b110 9
b1010 2
b1010 ?
b100 B
b1110 A
b110 .
b110 K
b1111000 !
b1111000 6
b1110 +
b1110 R
b1100 %
b1100 (
b1100 8
b1100 <
b1100 D
b1100 H
b1100 M
b1100 Q
b1111000 -
b1111000 N
b1010 $
b1010 '
b1010 7
b1010 ;
b1010 C
b1010 G
b1010 L
b1010 P
#300000
b10100000 0
b10100000 E
b0 I
b1 =
b1011 3
b1011 9
04
b101 2
b101 ?
b101 @
b1 >
b0 .
b0 K
0"
b1011 !
b1011 6
b1001 +
b1001 R
0,
b0 &
b0 *
b1010 -
b1010 N
b1 %
b1 (
b1 8
b1 <
b1 D
b1 H
b1 M
b1 Q
#310000
b1000 0
b1000 E
b11 I
14
1,
b1 3
b1 9
b100 2
b100 ?
b100 @
b0 .
b0 K
b1000 !
b1000 6
b1111 +
b1111 R
b11 &
b11 *
b1001 %
b1001 (
b1001 8
b1001 <
b1001 D
b1001 H
b1001 M
b1001 Q
b1001000 -
b1001000 N
b1000 $
b1000 '
b1000 7
b1000 ;
b1000 C
b1000 G
b1000 L
b1000 P
#320000
b10000 0
b10000 E
b10 I
b10 =
b10 >
0,
b1100 3
b1100 9
04
b1001 2
b1001 ?
b1001 @
b0 !
b0 6
b0 +
b0 R
b110 &
b110 *
b110 %
b110 (
b110 8
b110 <
b110 D
b110 H
b110 M
b110 Q
b100100 -
b100100 N
b110 $
b110 '
b110 7
b110 ;
b110 C
b110 G
b110 L
b110 P
